x402_secure_client/__init__.py
x402_secure_client/agent.py
x402_secure_client/buyer.py
x402_secure_client/headers.py
x402_secure_client/otel.py
x402_secure_client/risk.py
x402_secure_client/seller.py
x402_secure_client/tracing.py
x402_secure-0.1.4.dist-info/METADATA
x402_secure-0.1.4.dist-info/WHEEL
x402_secure-0.1.4.dist-info/RECORD
