Metadata-Version: 2.4
Name: x402-secure
Version: 0.1.4
Summary: Secure x402 client SDK with agentic payments for buyers and sellers
Author-email: t54 labs <dev@t54.ai>
License: Apache-2.0
Requires-Python: >=3.11
Requires-Dist: httpx>=0.25.0
Requires-Dist: openai>=2.3.0
Requires-Dist: opentelemetry-api>=1.24.0
Provides-Extra: agent
Requires-Dist: openai>=1.0.0; extra == 'agent'
Provides-Extra: examples
Requires-Dist: eth-account>=0.10.0; extra == 'examples'
Requires-Dist: eth-utils>=2.3.0; extra == 'examples'
Requires-Dist: fastapi>=0.104.0; extra == 'examples'
Requires-Dist: opentelemetry-exporter-otlp>=1.24.0; extra == 'examples'
Requires-Dist: opentelemetry-sdk>=1.24.0; extra == 'examples'
Requires-Dist: pydantic>=2.0.0; extra == 'examples'
Requires-Dist: python-dotenv>=1.0.0; extra == 'examples'
Requires-Dist: uvicorn>=0.24.0; extra == 'examples'
Requires-Dist: x402>=0.2.0; extra == 'examples'
Provides-Extra: otel
Requires-Dist: opentelemetry-exporter-otlp>=1.24.0; extra == 'otel'
Requires-Dist: opentelemetry-sdk>=1.24.0; extra == 'otel'
Provides-Extra: signing
Requires-Dist: eth-account>=0.10.0; extra == 'signing'
Requires-Dist: eth-utils>=2.3.0; extra == 'signing'
Requires-Dist: x402>=0.2.0; extra == 'signing'
